vectometry/__init__.py
vectometry-2021.8.dist-info/LICENSE.txt
vectometry-2021.8.dist-info/METADATA
vectometry-2021.8.dist-info/WHEEL
vectometry-2021.8.dist-info/top_level.txt
vectometry-2021.8.dist-info/RECORD
