Metadata-Version: 2.1
Name: vectometry
Version: 2021.8
Summary: A Python library for simple use of common point and vector operations in 3-dimensional space as well as for 2-dimensions.
Home-page: https://github.com/InformaticFreak/vectometry
Author: InformaticFreak
License: MIT
Project-URL: Documentation, https://github.com/InformaticFreak/vectometry#documentation
Project-URL: Source, https://github.com/InformaticFreak/vectometry/blob/main/src/vectometry/__init__.py
Project-URL: Bug Tracker, https://github.com/InformaticFreak/vectometry/issues
Project-URL: Change Log, https://github.com/InformaticFreak/vectometry/blob/main/CHANGELOG.md
Keywords: python,vector,point,geometry,analytic,vector-math,vectors-calculations,vectorspace,vectometry,vectors,2d,3d,vector2d,vector3d
Platform: UNKNOWN
Classifier: Development Status :: 4 - Beta
Classifier: Intended Audience :: Developers
Classifier: License :: OSI Approved :: MIT License
Classifier: Operating System :: OS Independent
Classifier: Programming Language :: Python
Classifier: Topic :: Scientific/Engineering :: Mathematics
Classifier: Topic :: Software Development :: Libraries :: Python Modules
Classifier: Topic :: Utilities
Requires-Python: >= 3.6
